sbsha69.py
sbsha69-9.0.0.dist-info/METADATA
sbsha69-9.0.0.dist-info/WHEEL
sbsha69-9.0.0.dist-info/top_level.txt
sbsha69-9.0.0.dist-info/RECORD
